README.md
aiotgbotapi/__init__.py
aiotgbotapi/bot.py
aiotgbotapi/bot_api_client.py
aiotgbotapi/errors.py
aiotgbotapi/filters.py
aiotgbotapi/types.py
aiotgbotapi/utils.py
aiotgbotapi-0.1.1.dist-info/WHEEL
aiotgbotapi-0.1.1.dist-info/METADATA
aiotgbotapi-0.1.1.dist-info/RECORD
