Metadata-Version: 2.1
Name: aiotgbotapi
Version: 0.1.1
Summary: Asynchronous Telegram BOT API Client
Home-page: https://github.com/pylakey/aiotgbotapi
License: MIT
Author: Pylakey
Author-email: pylakey@protonmail.com
Requires-Python: >=3.9,<4.0
Classifier: Framework :: AsyncIO
Classifier: License :: OSI Approved :: MIT License
Classifier: Operating System :: OS Independent
Classifier: Programming Language :: Python :: 3
Classifier: Programming Language :: Python :: 3.10
Classifier: Programming Language :: Python :: 3.9
Classifier: Topic :: Software Development :: Libraries :: Python Modules
Classifier: Typing :: Typed
Requires-Dist: fastapi (>=0.70.0,<0.71.0)
Requires-Dist: httpx[http2] (>=0.20.0,<0.21.0)
Requires-Dist: pydantic (>=1.8.2,<2.0.0)
Requires-Dist: ujson (>=4.2.0,<5.0.0)
Project-URL: Repository, https://github.com/pylakey/aiotgbotapi
